{
  "version": "6",
  "dialect": "sqlite",
  "id": "f81e3a01-1f59-4879-9dd4-c49af3ee6dd7",
  "prevId": "9f352a33-7786-480b-895f-69a603398a09",
  "tables": {
    "attachables": {
      "name": "attachables",
      "columns": {
        "id": {
          "name": "id",
          "type": "integer",
          "primaryKey": true,
          "notNull": true,
          "autoincrement": true
        },
        "attachmentId": {
          "name": "attachmentId",
          "type": "integer",
          "primaryKey": false,
          "notNull": true,
          "autoincrement": false
        },
        "recordId": {
          "name": "recordId",
          "type": "integer",
          "primaryKey": false,
          "notNull": false,
          "autoincrement": false
        },
        "patientId": {
          "name": "patientId",
          "type": "integer",
          "primaryKey": false,
          "notNull": false,
          "autoincrement": false
        },
        "medicineId": {
          "name": "medicineId",
          "type": "integer",
          "primaryKey": false,
          "notNull": false,
          "autoincrement": false
        }
      },
      "indexes": {},
      "foreignKeys": {
        "attachables_attachmentId_attachments_id_fk": {
          "name": "attachables_attachmentId_attachments_id_fk",
          "tableFrom": "attachables",
          "tableTo": "attachments",
          "columnsFrom": [
            "attachmentId"
          ],
          "columnsTo": [
            "id"
          ],
          "onDelete": "cascade",
          "onUpdate": "no action"
        },
        "attachables_recordId_records_id_fk": {
          "name": "attachables_recordId_records_id_fk",
          "tableFrom": "attachables",
          "tableTo": "records",
          "columnsFrom": [
            "recordId"
          ],
          "columnsTo": [
            "id"
          ],
          "onDelete": "cascade",
          "onUpdate": "no action"
        },
        "attachables_patientId_patients_id_fk": {
          "name": "attachables_patientId_patients_id_fk",
          "tableFrom": "attachables",
          "tableTo": "patients",
          "columnsFrom": [
            "patientId"
          ],
          "columnsTo": [
            "id"
          ],
          "onDelete": "cascade",
          "onUpdate": "no action"
        },
        "attachables_medicineId_medicines_id_fk": {
          "name": "attachables_medicineId_medicines_id_fk",
          "tableFrom": "attachables",
          "tableTo": "medicines",
          "columnsFrom": [
            "medicineId"
          ],
          "columnsTo": [
            "id"
          ],
          "onDelete": "cascade",
          "onUpdate": "no action"
        }
      },
      "compositePrimaryKeys": {},
      "uniqueConstraints": {},
      "checkConstraints": {}
    },
    "attachments": {
      "name": "attachments",
      "columns": {
        "id": {
          "name": "id",
          "type": "integer",
          "primaryKey": true,
          "notNull": true,
          "autoincrement": true
        },
        "uri": {
          "name": "uri",
          "type": "text",
          "primaryKey": false,
          "notNull": true,
          "autoincrement": false
        },
        "name": {
          "name": "name",
          "type": "text",
          "primaryKey": false,
          "notNull": true,
          "autoincrement": false
        },
        "createdAt": {
          "name": "createdAt",
          "type": "text",
          "primaryKey": false,
          "notNull": false,
          "autoincrement": false,
          "default": "(CURRENT_TIMESTAMP)"
        },
        "updatedAt": {
          "name": "updatedAt",
          "type": "text",
          "primaryKey": false,
          "notNull": false,
          "autoincrement": false,
          "default": "(CURRENT_TIMESTAMP)"
        }
      },
      "indexes": {},
      "foreignKeys": {},
      "compositePrimaryKeys": {},
      "uniqueConstraints": {},
      "checkConstraints": {}
    },
    "medicines": {
      "name": "medicines",
      "columns": {
        "id": {
          "name": "id",
          "type": "integer",
          "primaryKey": true,
          "notNull": true,
          "autoincrement": true
        },
        "name": {
          "name": "name",
          "type": "text",
          "primaryKey": false,
          "notNull": true,
          "autoincrement": false
        },
        "thumbnailId": {
          "name": "thumbnailId",
          "type": "integer",
          "primaryKey": false,
          "notNull": false,
          "autoincrement": false
        },
        "createdAt": {
          "name": "createdAt",
          "type": "text",
          "primaryKey": false,
          "notNull": false,
          "autoincrement": false,
          "default": "(CURRENT_TIMESTAMP)"
        },
        "updatedAt": {
          "name": "updatedAt",
          "type": "text",
          "primaryKey": false,
          "notNull": false,
          "autoincrement": false,
          "default": "(CURRENT_TIMESTAMP)"
        }
      },
      "indexes": {},
      "foreignKeys": {
        "medicines_thumbnailId_attachments_id_fk": {
          "name": "medicines_thumbnailId_attachments_id_fk",
          "tableFrom": "medicines",
          "tableTo": "attachments",
          "columnsFrom": [
            "thumbnailId"
          ],
          "columnsTo": [
            "id"
          ],
          "onDelete": "no action",
          "onUpdate": "no action"
        }
      },
      "compositePrimaryKeys": {},
      "uniqueConstraints": {},
      "checkConstraints": {}
    },
    "patient_medicines": {
      "name": "patient_medicines",
      "columns": {
        "id": {
          "name": "id",
          "type": "integer",
          "primaryKey": true,
          "notNull": true,
          "autoincrement": true
        },
        "patientId": {
          "name": "patientId",
          "type": "integer",
          "primaryKey": false,
          "notNull": false,
          "autoincrement": false
        },
        "medicineId": {
          "name": "medicineId",
          "type": "integer",
          "primaryKey": false,
          "notNull": false,
          "autoincrement": false
        },
        "startDate": {
          "name": "startDate",
          "type": "text",
          "primaryKey": false,
          "notNull": false,
          "autoincrement": false
        },
        "endDate": {
          "name": "endDate",
          "type": "text",
          "primaryKey": false,
          "notNull": false,
          "autoincrement": false
        },
        "schedule": {
          "name": "schedule",
          "type": "text",
          "primaryKey": false,
          "notNull": false,
          "autoincrement": false
        },
        "stock": {
          "name": "stock",
          "type": "integer",
          "primaryKey": false,
          "notNull": false,
          "autoincrement": false
        }
      },
      "indexes": {},
      "foreignKeys": {
        "patient_medicines_patientId_patients_id_fk": {
          "name": "patient_medicines_patientId_patients_id_fk",
          "tableFrom": "patient_medicines",
          "tableTo": "patients",
          "columnsFrom": [
            "patientId"
          ],
          "columnsTo": [
            "id"
          ],
          "onDelete": "cascade",
          "onUpdate": "no action"
        },
        "patient_medicines_medicineId_medicines_id_fk": {
          "name": "patient_medicines_medicineId_medicines_id_fk",
          "tableFrom": "patient_medicines",
          "tableTo": "medicines",
          "columnsFrom": [
            "medicineId"
          ],
          "columnsTo": [
            "id"
          ],
          "onDelete": "cascade",
          "onUpdate": "no action"
        }
      },
      "compositePrimaryKeys": {},
      "uniqueConstraints": {},
      "checkConstraints": {}
    },
    "patients": {
      "name": "patients",
      "columns": {
        "id": {
          "name": "id",
          "type": "integer",
          "primaryKey": true,
          "notNull": true,
          "autoincrement": true
        },
        "name": {
          "name": "name",
          "type": "text",
          "primaryKey": false,
          "notNull": true,
          "autoincrement": false
        },
        "dob": {
          "name": "dob",
          "type": "text",
          "primaryKey": false,
          "notNull": false,
          "autoincrement": false
        },
        "gender": {
          "name": "gender",
          "type": "text",
          "primaryKey": false,
          "notNull": false,
          "autoincrement": false
        },
        "edd": {
          "name": "edd",
          "type": "text",
          "primaryKey": false,
          "notNull": false,
          "autoincrement": false
        },
        "avatarId": {
          "name": "avatarId",
          "type": "integer",
          "primaryKey": false,
          "notNull": false,
          "autoincrement": false
        },
        "createdAt": {
          "name": "createdAt",
          "type": "text",
          "primaryKey": false,
          "notNull": false,
          "autoincrement": false,
          "default": "(CURRENT_TIMESTAMP)"
        },
        "updatedAt": {
          "name": "updatedAt",
          "type": "text",
          "primaryKey": false,
          "notNull": false,
          "autoincrement": false,
          "default": "(CURRENT_TIMESTAMP)"
        }
      },
      "indexes": {},
      "foreignKeys": {
        "patients_avatarId_attachments_id_fk": {
          "name": "patients_avatarId_attachments_id_fk",
          "tableFrom": "patients",
          "tableTo": "attachments",
          "columnsFrom": [
            "avatarId"
          ],
          "columnsTo": [
            "id"
          ],
          "onDelete": "no action",
          "onUpdate": "no action"
        }
      },
      "compositePrimaryKeys": {},
      "uniqueConstraints": {},
      "checkConstraints": {}
    },
    "records": {
      "name": "records",
      "columns": {
        "id": {
          "name": "id",
          "type": "integer",
          "primaryKey": true,
          "notNull": true,
          "autoincrement": true
        },
        "text": {
          "name": "text",
          "type": "text",
          "primaryKey": false,
          "notNull": false,
          "autoincrement": false
        },
        "date": {
          "name": "date",
          "type": "text",
          "primaryKey": false,
          "notNull": true,
          "autoincrement": false
        },
        "amount": {
          "name": "amount",
          "type": "integer",
          "primaryKey": false,
          "notNull": true,
          "autoincrement": false,
          "default": 0
        },
        "patientId": {
          "name": "patientId",
          "type": "integer",
          "primaryKey": false,
          "notNull": false,
          "autoincrement": false
        },
        "createdAt": {
          "name": "createdAt",
          "type": "text",
          "primaryKey": false,
          "notNull": false,
          "autoincrement": false,
          "default": "(CURRENT_TIMESTAMP)"
        },
        "updatedAt": {
          "name": "updatedAt",
          "type": "text",
          "primaryKey": false,
          "notNull": false,
          "autoincrement": false,
          "default": "(CURRENT_TIMESTAMP)"
        }
      },
      "indexes": {
        "date_idx": {
          "name": "date_idx",
          "columns": [
            "date"
          ],
          "isUnique": false
        },
        "patient_id_idx": {
          "name": "patient_id_idx",
          "columns": [
            "patientId"
          ],
          "isUnique": false
        }
      },
      "foreignKeys": {
        "records_patientId_patients_id_fk": {
          "name": "records_patientId_patients_id_fk",
          "tableFrom": "records",
          "tableTo": "patients",
          "columnsFrom": [
            "patientId"
          ],
          "columnsTo": [
            "id"
          ],
          "onDelete": "cascade",
          "onUpdate": "no action"
        }
      },
      "compositePrimaryKeys": {},
      "uniqueConstraints": {},
      "checkConstraints": {}
    },
    "taggables": {
      "name": "taggables",
      "columns": {
        "id": {
          "name": "id",
          "type": "integer",
          "primaryKey": true,
          "notNull": true,
          "autoincrement": true
        },
        "tagId": {
          "name": "tagId",
          "type": "integer",
          "primaryKey": false,
          "notNull": false,
          "autoincrement": false
        },
        "recordId": {
          "name": "recordId",
          "type": "integer",
          "primaryKey": false,
          "notNull": false,
          "autoincrement": false
        }
      },
      "indexes": {},
      "foreignKeys": {
        "taggables_tagId_tags_id_fk": {
          "name": "taggables_tagId_tags_id_fk",
          "tableFrom": "taggables",
          "tableTo": "tags",
          "columnsFrom": [
            "tagId"
          ],
          "columnsTo": [
            "id"
          ],
          "onDelete": "cascade",
          "onUpdate": "no action"
        },
        "taggables_recordId_records_id_fk": {
          "name": "taggables_recordId_records_id_fk",
          "tableFrom": "taggables",
          "tableTo": "records",
          "columnsFrom": [
            "recordId"
          ],
          "columnsTo": [
            "id"
          ],
          "onDelete": "cascade",
          "onUpdate": "no action"
        }
      },
      "compositePrimaryKeys": {},
      "uniqueConstraints": {},
      "checkConstraints": {}
    },
    "tags": {
      "name": "tags",
      "columns": {
        "id": {
          "name": "id",
          "type": "integer",
          "primaryKey": true,
          "notNull": true,
          "autoincrement": true
        },
        "name": {
          "name": "name",
          "type": "text",
          "primaryKey": false,
          "notNull": true,
          "autoincrement": false
        }
      },
      "indexes": {
        "tags_name_unique": {
          "name": "tags_name_unique",
          "columns": [
            "name"
          ],
          "isUnique": true
        },
        "name_idx": {
          "name": "name_idx",
          "columns": [
            "name"
          ],
          "isUnique": false
        }
      },
      "foreignKeys": {},
      "compositePrimaryKeys": {},
      "uniqueConstraints": {},
      "checkConstraints": {}
    }
  },
  "views": {},
  "enums": {},
  "_meta": {
    "schemas": {},
    "tables": {},
    "columns": {}
  },
  "internal": {
    "indexes": {}
  }
}